setup.py
cmd.pop.egg-info/PKG-INFO
cmd.pop.egg-info/SOURCES.txt
cmd.pop.egg-info/dependency_links.txt
cmd.pop.egg-info/requires.txt
cmd.pop.egg-info/top_level.txt
cmd_html/HTML.py
cmd_html/HTML_del.py
cmd_html/HTML_init.py
cmd_html/__init__.py
cmd_html/moon_app.py
cmd_html/setupPIP.py
cmd_pop/__init__.py
cmd_pop/load_text.py
cmd_pop/pypi.py
cmd_pop/pypiDIR.py
cmd_pop/setupB.py
cmd_pop/up.py
cmd_pop/uuu.py
cmd_pop/uuu_ABC.py
cmd_pypi/Box.py
cmd_pypi/BoxBox.py
cmd_pypi/HTML2.py
cmd_pypi/__init__.py