Metadata-Version: 2.1
Name: cmd.pop
Version: 0.23.0
Summary: 笨貓魔法
License: LGPL
